{
  "repo": "morgan-lewis",
  "feeds": [
    {
      "source": "https://www.morganlewis.com/blogs",
      "feed_url": "",
      "saved": 0,
      "method": "agent-scrape"
    },
    {
      "source": "https://www.morganlewis.com/blogs/governmentcontractorguidebook",
      "feed_url": "",
      "saved": 1,
      "method": "agent-scrape"
    },
    {
      "source": "https://www.morganlewis.com/blogs/upandatom",
      "feed_url": "",
      "saved": 0,
      "method": "agent-scrape"
    }
  ],
  "post_count": 11,
  "fetched": "2026-06-27T12:55:03Z",
  "agent_pulled": "2026-06-27"
}
